[
	[
		{
			"title": "BEEE",
			"venue": "SMVG10",
			"timings": [
				16,
				0,
				16,
				50
			]
		},
		{
			"title": "Chemistry",
			"venue": "PRP120",
			"timings": [
				17,
				0,
				17,
				50
			]
		},
		{
			"title": "QSP",
			"venue": "TT415",
			"timings": [
				18,
				0,
				11,
				30
			]
		}
	],
	[
		{
			"title": "English",
			"venue": "MB309",
			"timings": [
				8,
				0,
				8,
				50
			]
		},
		{
			"title": "Chemistry",
			"venue": "PRP120",
			"timings": [
				14,
				0,
				14,
				50
			]
		},
		{
			"title": "QSP",
			"venue": "TT415",
			"timings": [
				15,
				0,
				15,
				50
			]
		},
		{
			"title": "Differential Equations",
			"venue": "TT414",
			"timings": [
				17,
				0,
				11,
				30
			]
		}
	],
	[
		{
			"title": "Differential Equations",
			"venue": "TT414",
			"timings": [
				14,
				0,
				14,
				50
			]
		},
		{
			"title": "BEEE",
			"venue": "SMVG10",
			"timings": [
				17,
				0,
				9,
				40
			]
		}
	],
	[
		{
			"title": "English",
			"venue": "MB309",
			"timings": [
				9,
				0,
				9,
				50
			]
		},
		{
			"title": "Java",
			"venue": "MB307A",
			"timings": [
				12,
				0,
				12,
				50
			]
		},
		{
			"title": "BEEE",
			"venue": "SMVG10",
			"timings": [
				14,
				0,
				14,
				50
			]
		},
		{
			"title": "Chemistry",
			"venue": "PRP120",
			"timings": [
				15,
				0,
				15,
				50
			]
		},
		{
			"title": "QSP",
			"venue": "TT415",
			"timings": [
				16,
				0,
				16,
				50
			]
		},
		{
			"title": "Differential Equations",
			"venue": "TT414",
			"timings": [
				18,
				0,
				18,
				50
			]
		}
	],
	[
		{
			"title": "Differential Equations",
			"venue": "TT414",
			"timings": [
				15,
				0,
				9,
				40
			]
		},
		{
			"title": "English Lab",
			"venue": "SJT701",
			"timings": [
				15,
				51,
				17,
				30
			]
		}
	],
	[
		{
			"title": "Chemistry",
			"venue": "PRP120",
			"timings": [
				15,
				50,
				16,
				10
			]
		}
	],
	[]
]