[
	[
		{
			"title": "Complex Variables",
			"venue": "MB107",
			"timings": [
				8,
				0,
				8,
				50
			]
		},
		{
			"title": "DSD",
			"venue": "TT523",
			"timings": [
				9,
				0,
				9,
				50
			]
		},
		{
			"title": "BECE205",
			"venue": "TT523",
			"timings": [
				10,
				0,
				10,
				50
			]
		},
		{
			"title": "BECE202",
			"venue": "TT504",
			"timings": [
				11,
				0,
				11,
				50
			]
		},
		{
			"title": "BECE206",
			"venue": "TT530",
			"timings": [
				12,
				0,
				12,
				50
			]
		},
		{
			"title": "BECE209 Lab",
			"venue": "TT134",
			"timings": [
				14,
				0,
				15,
				40
			]
		}
	],
	[
		{
			"title": "BECE202",
			"venue": "TT504",
			"timings": [
				8,
				0,
				8,
				50
			]
		},
		{
			"title": "BECE206",
			"venue": "TT530",
			"timings": [
				9,
				0,
				9,
				50
			]
		},
		{
			"title": "QSP",
			"venue": "TT504",
			"timings": [
				10,
				0,
				10,
				50
			]
		},
		{
			"title": "Complex Variables",
			"venue": "MB107",
			"timings": [
				12,
				0,
				12,
				50
			]
		},
		{
			"title": "DSD Lab",
			"venue": "TT422",
			"timings": [
				14,
				0,
				15,
				40
			]
		},
		{
			"title": "BECE206 Lab",
			"venue": "TT246",
			"timings": [
				17,
				40,
				19,
				20
			]
		}
	],
	[
		{
			"title": "BECE209",
			"venue": "TT104",
			"timings": [
				8,
				0,
				8,
				50
			]
		},
		{
			"title": "Complex Variables",
			"venue": "MB107",
			"timings": [
				9,
				0,
				9,
				50
			]
		},
		{
			"title": "DSD",
			"venue": "TT523",
			"timings": [
				10,
				0,
				10,
				50
			]
		}
	],
	[
		{
			"title": "BECE205",
			"venue": "TT523",
			"timings": [
				8,
				0,
				8,
				50
			]
		},
		{
			"title": "BECE202",
			"venue": "TT504",
			"timings": [
				9,
				0,
				9,
				50
			]
		},
		{
			"title": "BECE206",
			"venue": "TT530",
			"timings": [
				10,
				0,
				10,
				50
			]
		},
		{
			"title": "QSP",
			"venue": "TT504",
			"timings": [
				11,
				0,
				11,
				50
			]
		}
	],
	[
		{
			"title": "QSP",
			"venue": "TT504",
			"timings": [
				8,
				0,
				8,
				50
			]
		},
		{
			"title": "BECE209",
			"venue": "TT104",
			"timings": [
				9,
				0,
				9,
				50
			]
		},
		{
			"title": "Complex Variables",
			"venue": "MB107",
			"timings": [
				10,
				0,
				10,
				50
			]
		},
		{
			"title": "DSD",
			"venue": "TT523",
			"timings": [
				11,
				0,
				11,
				50
			]
		},
		{
			"title": "BECE205",
			"venue": "TT523",
			"timings": [
				12,
				0,
				12,
				50
			]
		},
		{
			"title": "Tech Report Writing Lab",
			"venue": "SJT720",
			"timings": [
				14,
				0,
				15,
				40
			]
		},
		{
			"title": "BECE209 Lab",
			"venue": "TT134",
			"timings": [
				17,
				40,
				19,
				20
			]
		}
	],
	[],
	[]
]